pypi_test_idiomatik/__init__.py
pypi_test_idiomatik/example.py
test_pypi_project_idiomatik-0.2.7.dist-info/LICENCE.txt
test_pypi_project_idiomatik-0.2.7.dist-info/METADATA
test_pypi_project_idiomatik-0.2.7.dist-info/WHEEL
test_pypi_project_idiomatik-0.2.7.dist-info/top_level.txt
test_pypi_project_idiomatik-0.2.7.dist-info/RECORD
