Metadata-Version: 2.1
Name: test-pypi-project-idiomatik
Version: 0.2.7
Summary: Test project, implements Fibonacci and Tribonacci functions
Author-email: Timmy McKimmy <TMcK@example.com>
Classifier: Programming Language :: Python :: 3
Classifier: License :: OSI Approved :: MIT License
Classifier: Operating System :: OS Independent
Classifier: Environment :: Console
Requires-Python: >=3.10
License-File: LICENCE.txt
Requires-Dist: httpx[http2] >=0.24
